uq_calculator/__init__.py
uq_calculator/evaluate_all.py
uq_calculator/get_ece.py
uq_calculator/get_mcd.py
uq_calculator/get_mcd_old.py
uq_calculator/get_nll.py
uq_calculator/plot_confidence_band.py
uq_calculator/uq_vis2.py
uq_calculator-0.1.4.dist-info/METADATA
uq_calculator-0.1.4.dist-info/WHEEL
uq_calculator-0.1.4.dist-info/RECORD
